[
    {
        "name": "John",
        "surname": "Doe",
        "email": "Ajohn.doe@example.com",
        "nationality": "Algerian",
        "phoneNumber": "1234567890",
        "drivingLicence": "BC12345"
    },
    {
        "name": "Jane",
        "surname": "Smith",
        "email": "jane.smith@example.com",
        "nationality": "Algerian",
        "phoneNumber": "9876543210",
        "drivingLicence": "YZ67890"
    },
    {
        "name": "Alice",
        "surname": "Brown",
        "email": "alice.brown@example.com",
        "nationality": "Algerian",
        "phoneNumber": "4561237890",
        "drivingLicence": "LMN4567"
    },
    {
        "name": "Bob",
        "surname": "White",
        "email": "bob.white@example.com",
        "nationality": "Algerian",
        "phoneNumber": "7894561230",
        "drivingLicence": "PQR12345"
    },
    {
        "name": "Charlie",
        "surname": "Black",
        "email": "charlie.black@example.com",
        "nationality": "Algerian",
        "phoneNumber": "3216549870",
        "drivingLicence": "mGHI98765"
    },
    {
        "name": "Emily",
        "surname": "Green",
        "email": "emily.green@example.com",
        "nationality": "Algerian",
        "phoneNumber": "6549873210",
        "drivingLicence": "TUV65432"
    },
    {
        "name": "David",
        "surname": "Gray",
        "email": "david.gray@example.com",
        "nationality": "Algerian",
        "phoneNumber": "7891234560",
        "drivingLicence": "DEF32145"
    },
    {
        "name": "Sophia",
        "surname": "Blue",
        "email": "sophia.blue@example.com",
        "nationality": "Algerian",
        "phoneNumber": "1597534860",
        "drivingLicence": "KLM78912"
    },
    {
        "name": "Lucas",
        "surname": "Orange",
        "email": "lucas.orange@example.com",
        "nationality": "Algerian",
        "phoneNumber": "9517534860",
        "drivingLicence": "NOP85246"
    },
    {
        "name": "Olivia",
        "surname": "Yellow",
        "email": "olivia.yellow@example.com",
        "nationality": "Algerian",
        "phoneNumber": "3579514860",
        "drivingLicence": "QRS74125"
    }
]
